{
  "user_query": "I am planning a trip to Singapore and I want to explore the local food scene. Can you recommend some popular restaurants in the city? Additionally, I would like to know the ingredients used in a specific makeup product from Sephora. Could you provide me with the details?",
  "domain": "Tourism",
  "TaskList": [
    {
      "id": 1,
      "description": "Gather information on popular restaurants in Singapore.",
      "domain": "tourism",
      "required_inputs": [
        "location",
        "cuisine_type"
      ]
    },
    {
      "id": 2,
      "description": "Fetch detailed ingredients of a specific makeup product from Sephora.",
      "domain": "tourism",
      "required_inputs": [
        "product_name",
        "brand"
      ]
    }
  ]
}