{
  "user_query": "I want to plan a hiking trip with weather forecast, music recommendations, and scenic trails.",
  "domain": "Tourism",
  "TaskList": [
    {
      "id": 1,
      "description": "Fetch the 5-day weather forecast for a popular mountain destination.",
      "domain": "tourism",
      "required_inputs": [
        "destination"
      ]
    },
    {
      "id": 2,
      "description": "Retrieve a list of uplifting songs from the music charts.",
      "domain": "tourism",
      "required_inputs": []
    },
    {
      "id": 3,
      "description": "Suggest scenic hiking trails or viewpoints in the chosen mountain destination.",
      "domain": "tourism",
      "required_inputs": [
        "destination"
      ]
    }
  ]
}