{
  "user_query": "I'm planning a trip and I want to explore the local culture and attractions. Fetch me a map tile with labels in the local language for a specific area. Additionally, suggest some webcams in that area to get a glimpse of the local lifestyle.",
  "domain": "Tourism",
  "TaskList": [
    {
      "id": 1,
      "description": "Fetch a map tile for the specified area with labels in the local language.",
      "domain": "tourism",
      "required_inputs": [
        "specific_area",
        "local_language"
      ]
    },
    {
      "id": 2,
      "description": "Suggest webcams in the specified area to observe the local lifestyle.",
      "domain": "tourism",
      "required_inputs": [
        "specific_area"
      ]
    }
  ]
}