{
  "user_query": "I want to know the daily dividend data for the stock symbol AAPL from March 2, 2022, to March 3, 2022, and fetch the historical price data and stock profile data.",
  "domain": "Finance",
  "TaskList": [
    {
      "id": 1,
      "description": "Fetch daily dividend data for the stock symbol AAPL from March 2, 2022, to March 3, 2022.",
      "domain": "finance",
      "required_inputs": [
        "stock_symbol",
        "start_date",
        "end_date"
      ]
    },
    {
      "id": 2,
      "description": "Fetch historical price data for the stock symbol AAPL.",
      "domain": "finance",
      "required_inputs": [
        "stock_symbol"
      ]
    },
    {
      "id": 3,
      "description": "Fetch stock profile data for the stock symbol AAPL.",
      "domain": "finance",
      "required_inputs": [
        "stock_symbol"
      ]
    }
  ]
}