{
  "user_query": "I am planning a family vacation in Austria and I want to ensure I have access to my bank account during the trip. Can you provide me with a list of supported banks in Austria and the required login form fields? Additionally, it would be helpful to retrieve the categories for transactions to keep track of our expenses.",
  "domain": "Finance",
  "TaskList": [
    {
      "id": 1,
      "description": "Retrieve a list of supported banks in Austria.",
      "domain": "finance",
      "required_inputs": []
    },
    {
      "id": 2,
      "description": "Get the required login form fields for accessing bank accounts for the obtained banks.",
      "domain": "finance",
      "required_inputs": [
        "list_of_banks"
      ]
    },
    {
      "id": 3,
      "description": "Fetch transaction categories to help keep track of expenses during the trip.",
      "domain": "finance",
      "required_inputs": []
    }
  ]
}