{
  "user_query": "I'm a fitness enthusiast and I'm looking for energetic music to keep me motivated during my workouts. Can you recommend some high-energy playlists and artists? It would also be great if you could share some trivia facts about the benefits of exercise and physical activity.",
  "domain": "Medical",
  "TaskList": [
    {
      "id": 1,
      "description": "Search for high-energy music playlists and artists suitable for workouts.",
      "domain": "medical",
      "required_inputs": [
        "music genre",
        "energy level"
      ]
    },
    {
      "id": 2,
      "description": "Retrieve trivia facts about the benefits of exercise and physical activity.",
      "domain": "medical",
      "required_inputs": [
        "topic",
        "specific benefits"
      ]
    }
  ]
}