{
  "user_query": "I want to organize my photo library efficiently and list all photos along with their details and file versions for specific photos.",
  "domain": "Technology",
  "TaskList": [
    {
      "id": 1,
      "description": "Retrieve a list of all photos stored in the user's photo library including their details such as file size, resolution, and date taken.",
      "domain": "technology",
      "required_inputs": []
    },
    {
      "id": 2,
      "description": "Get the available file versions for a specific photo identified by the user.",
      "domain": "technology",
      "required_inputs": [
        "photo_id"
      ]
    }
  ]
}