{
  "user_query": "I want to stay up-to-date with the latest releases from popular artists and get playlist suggestions.",
  "domain": "Technology",
  "TaskList": [
    {
      "id": 1,
      "description": "Query the latest music releases from popular artists across different genres and countries.",
      "domain": "technology",
      "required_inputs": [
        "genres",
        "countries"
      ]
    },
    {
      "id": 2,
      "description": "Retrieve recommended playlists based on different moods and occasions.",
      "domain": "technology",
      "required_inputs": [
        "moods",
        "occasions"
      ]
    }
  ]
}