{
  "user_query": "Find the translation of the sentence 'How are you today?' into Old English. Furthermore, give me the Scrabble score for the word 'fantastic'. Additionally, provide me with the antonyms of the word 'fast'.",
  "domain": "Technology",
  "TaskList": [
    {
      "id": 1,
      "description": "Translate the sentence 'How are you today?' into Old English.",
      "domain": "technology",
      "required_inputs": [
        "sentence"
      ]
    },
    {
      "id": 2,
      "description": "Calculate the Scrabble score for the word 'fantastic'.",
      "domain": "technology",
      "required_inputs": [
        "word"
      ]
    },
    {
      "id": 3,
      "description": "Find the antonyms for the word 'fast'.",
      "domain": "technology",
      "required_inputs": [
        "word"
      ]
    }
  ]
}