{
  "user_query": "I'm writing a book on the benefits of humor in the workplace. Can you provide me with a quote about humor and a funny Chuck Norris joke to include in the book? Additionally, fetch jokes from the Jokes by API-Ninjas API to provide more examples of workplace humor.",
  "domain": "Technology",
  "TaskList": [
    {
      "id": 1,
      "description": "Fetch a quote about humor.",
      "domain": "technology",
      "required_inputs": [
        "quote_topic"
      ]
    },
    {
      "id": 2,
      "description": "Fetch a funny Chuck Norris joke.",
      "domain": "technology",
      "required_inputs": [
        "joke_topic"
      ]
    },
    {
      "id": 3,
      "description": "Fetch a collection of jokes from the Jokes by API-Ninjas API.",
      "domain": "technology",
      "required_inputs": [
        "category"
      ]
    }
  ]
}