{
  "user_query": "I want to fetch the latest odds for matches in the Bildbet sports category and provide the details for our website.",
  "domain": "Finance",
  "TaskList": [
    {
      "id": 1,
      "description": "Fetch the latest odds for matches in the Bildbet sports category.",
      "domain": "finance",
      "required_inputs": [
        "sports_category"
      ]
    },
    {
      "id": 2,
      "description": "Retrieve the detailed information of the matches associated with the fetched odds.",
      "domain": "finance",
      "required_inputs": [
        "odds_data_id"
      ]
    }
  ]
}